[{"id":766453,"title":"Hummus and Za'atar","image":"https://spoonacular.com/recipeImages/766453-312x231.jpg","imageType":"jpg","nutrition":{"nutrients":[{"name":"Calories","amount":778.275,"unit":"kcal"}]}},{"id":716195,"title":"Spicy Indian-Style Hummus","image":"https://spoonacular.com/recipeImages/716195-312x231.jpg","imageType":"jpg","nutrition":{"nutrients":[{"name":"Calories","amount":133.791,"unit":"kcal"}]}},{"id":649411,"title":"Lebanese Tabouleh","image":"https://spoonacular.com/recipeImages/649411-312x231.jpg","imageType":"jpg","nutrition":{"nutrients":[{"name":"Calories","amount":241.341,"unit":"kcal"}]}},{"id":642121,"title":"Easy Tabouleh","image":"https://spoonacular.com/recipeImages/642121-312x231.jpg","imageType":"jpg","nutrition":{"nutrients":[{"name":"Calories","amount":716.7,"unit":"kcal"}]}},{"id":649405,"title":"Lebanese Lentil Soup","image":"https://spoonacular.com/recipeImages/649405-312x231.jpg","imageType":"jpg","nutrition":{"nutrients":[{"name":"Calories","amount":393.418,"unit":"kcal"}]}},{"id":665378,"title":"Winter Fattoush Salad","image":"https://spoonacular.com/recipeImages/665378-312x231.jpg","imageType":"jpg","nutrition":{"nutrients":[{"name":"Calories","amount":345.88,"unit":"kcal"}]}},{"id":647638,"title":"Hummus Wrap With Carrots and Cucumbers","image":"https://spoonacular.com/recipeImages/647638-312x231.jpg","imageType":"jpg","nutrition":{"nutrients":[{"name":"Calories","amount":860.561,"unit":"kcal"}]}},{"id":647634,"title":"Hummus with roasted orange peppers","image":"https://spoonacular.com/recipeImages/647634-312x231.jpg","imageType":"jpg","nutrition":{"nutrients":[{"name":"Calories","amount":387.341,"unit":"kcal"}]}},{"id":651832,"title":"Middle Eastern Stuffed Lentil Zatar Bread","image":"https://spoonacular.com/recipeImages/651832-312x231.jpg","imageType":"jpg","nutrition":{"nutrients":[{"name":"Calories","amount":471.24,"unit":"kcal"}]}},{"id":658573,"title":"Roasted Eggplant Hummus","image":"https://spoonacular.com/recipeImages/658573-312x231.jpg","imageType":"jpg","nutrition":{"nutrients":[{"name":"Calories","amount":255.247,"unit":"kcal"}]}},{"id":639950,"title":"Colorful Red Quinoa Not So Tabbouleh Salad","image":"https://spoonacular.com/recipeImages/639950-312x231.jpg","imageType":"jpg","nutrition":{"nutrients":[{"name":"Calories","amount":283.318,"unit":"kcal"}]}},{"id":651823,"title":"Middle Eastern Chopped Salad","image":"https://spoonacular.com/recipeImages/651823-312x231.jpg","imageType":"jpg","nutrition":{"nutrients":[{"name":"Calories","amount":155.923,"unit":"kcal"}]}},{"id":649407,"title":"Lebanese Falafel","image":"https://spoonacular.com/recipeImages/649407-312x231.jpg","imageType":"jpg","nutrition":{"nutrients":[{"name":"Calories","amount":480.735,"unit":"kcal"}]}},{"id":642547,"title":"Indian-Inspired Falafel Appetizer","image":"https://spoonacular.com/recipeImages/642547-312x231.jpg","imageType":"jpg","nutrition":{"nutrients":[{"name":"Calories","amount":89.2033,"unit":"kcal"}]}},{"id":638316,"title":"Chicken Shawarma Bowl","image":"https://spoonacular.com/recipeImages/638316-312x231.jpg","imageType":"jpg","nutrition":{"nutrients":[{"name":"Calories","amount":697.74,"unit":"kcal"}]}},{"id":657686,"title":"Quinoa Tabbouleh Salad","image":"https://spoonacular.com/recipeImages/657686-312x231.jpg","imageType":"jpg","nutrition":{"nutrients":[{"name":"Calories","amount":135.669,"unit":"kcal"}]}},{"id":647636,"title":"Hummus With Tahini Sauce","image":"https://spoonacular.com/recipeImages/647636-312x231.jpg","imageType":"jpg","nutrition":{"nutrients":[{"name":"Calories","amount":370.95,"unit":"kcal"}]}},{"id":642539,"title":"Falafel Burger","image":"https://spoonacular.com/recipeImages/642539-312x231.png","imageType":"png","nutrition":{"nutrients":[{"name":"Calories","amount":402.324,"unit":"kcal"}]}},{"id":1697571,"title":"Zhoug Sauce (aka Schug Sauce) – A Spicy Middle Eastern Cilantro Sauce","image":"https://spoonacular.com/recipeImages/1697571-312x231.jpg","imageType":"jpg","nutrition":{"nutrients":[{"name":"Calories","amount":66.7,"unit":"kcal"}]}},{"id":645704,"title":"Grilled Fattoush","image":"https://spoonacular.com/recipeImages/645704-312x231.jpg","imageType":"jpg","nutrition":{"nutrients":[{"name":"Calories","amount":296.64,"unit":"kcal"}]}},{"id":642893,"title":"Fire-Roasted Jalapeño Hummus with Turnip and Beet Chips","image":"https://spoonacular.com/recipeImages/642893-312x231.jpg","imageType":"jpg","nutrition":{"nutrients":[{"name":"Calories","amount":344.173,"unit":"kcal"}]}},{"id":637481,"title":"Chavrie Tabbouleh","image":"https://spoonacular.com/recipeImages/637481-312x231.jpg","imageType":"jpg","nutrition":{"nutrients":[{"name":"Calories","amount":251.362,"unit":"kcal"}]}},{"id":649413,"title":"Lebanese Sweet Tahini Swirls","image":"https://spoonacular.com/recipeImages/649413-312x231.jpg","imageType":"jpg","nutrition":{"nutrients":[{"name":"Calories","amount":252.911,"unit":"kcal"}]}},{"id":649403,"title":"Lebanese Kibbeh","image":"https://spoonacular.com/recipeImages/649403-312x231.jpg","imageType":"jpg","nutrition":{"nutrients":[{"name":"Calories","amount":583.243,"unit":"kcal"}]}},{"id":634431,"title":"Basil Lime White Bean Hummus","image":"https://spoonacular.com/recipeImages/634431-312x231.jpg","imageType":"jpg","nutrition":{"nutrients":[{"name":"Calories","amount":95.9653,"unit":"kcal"}]}},{"id":642169,"title":"Edamame Hummus","image":"https://spoonacular.com/recipeImages/642169-312x231.jpg","imageType":"jpg","nutrition":{"nutrients":[{"name":"Calories","amount":176.822,"unit":"kcal"}]}},{"id":647109,"title":"Homemade Spiced Hummus & Pita","image":"https://spoonacular.com/recipeImages/647109-312x231.jpg","imageType":"jpg","nutrition":{"nutrients":[{"name":"Calories","amount":402.972,"unit":"kcal"}]}},{"id":655316,"title":"Peanut Butter Hummus","image":"https://spoonacular.com/recipeImages/655316-312x231.jpg","imageType":"jpg","nutrition":{"nutrients":[{"name":"Calories","amount":147.232,"unit":"kcal"}]}},{"id":637476,"title":"Chavrie Hummus","image":"https://spoonacular.com/recipeImages/637476-312x231.jpg","imageType":"jpg","nutrition":{"nutrients":[{"name":"Calories","amount":194.869,"unit":"kcal"}]}},{"id":647631,"title":"Hummus Soup","image":"https://spoonacular.com/recipeImages/647631-312x231.jpg","imageType":"jpg","nutrition":{"nutrients":[{"name":"Calories","amount":60.8763,"unit":"kcal"}]}},{"id":639410,"title":"Cilantro Hummus","image":"https://spoonacular.com/recipeImages/639410-312x231.jpg","imageType":"jpg","nutrition":{"nutrients":[{"name":"Calories","amount":75.444,"unit":"kcal"}]}},{"id":634389,"title":"Basic Hummus","image":"https://spoonacular.com/recipeImages/634389-312x231.jpg","imageType":"jpg","nutrition":{"nutrients":[{"name":"Calories","amount":39.564,"unit":"kcal"}]}},{"id":658503,"title":"Roasted Beet Hummus","image":"https://spoonacular.com/recipeImages/658503-312x231.jpg","imageType":"jpg","nutrition":{"nutrients":[{"name":"Calories","amount":195.79,"unit":"kcal"}]}},{"id":640834,"title":"Crispy Rosemary Hummus","image":"https://spoonacular.com/recipeImages/640834-312x231.jpg","imageType":"jpg","nutrition":{"nutrients":[{"name":"Calories","amount":96.1154,"unit":"kcal"}]}},{"id":636422,"title":"Buffalo Wing Hummus","image":"https://spoonacular.com/recipeImages/636422-312x231.jpg","imageType":"jpg","nutrition":{"nutrients":[{"name":"Calories","amount":37.2137,"unit":"kcal"}]}},{"id":631783,"title":"Honeyed Bacon\" Baklava","image":"https://spoonacular.com/recipeImages/631783-312x231.jpg","imageType":"jpg","nutrition":{"nutrients":[{"name":"Calories","amount":395.236,"unit":"kcal"}]}}]